mcp_git_explorer/__init__.py
mcp_git_explorer/cli.py
mcp_git_explorer/core.py
mcp_git_explorer/settings.py
mcp_git_explorer-0.3.0.dist-info/METADATA
mcp_git_explorer-0.3.0.dist-info/WHEEL
mcp_git_explorer-0.3.0.dist-info/entry_points.txt
mcp_git_explorer-0.3.0.dist-info/licenses/LICENSE
mcp_git_explorer-0.3.0.dist-info/RECORD
