Metadata-Version: 2.4
Name: mcp-git-explorer
Version: 0.3.0
Summary: Simple MCP server for fetching the remote git repository content as a structured text file
Project-URL: Homepage, https://github.com/jmiedzinski/mcp-git-explorer
Project-URL: Issues, https://github.com/jmiedzinski/mcp-git-explorer/issues
Author-email: Jeremiasz Miedzinski <jmiedzinski+mcp-git-explorer@gmail.com>
License: MIT
License-File: LICENSE
Classifier: Development Status :: 4 - Beta
Classifier: Intended Audience :: Developers
Classifier: License :: OSI Approved :: MIT License
Classifier: Programming Language :: Python :: 3
Classifier: Programming Language :: Python :: 3.10
Classifier: Programming Language :: Python :: 3.11
Classifier: Programming Language :: Python :: 3.12
Requires-Python: >=3.10
Requires-Dist: gitpython>=3.1.44
Requires-Dist: mcp[cli]>=1.6.0
Requires-Dist: tiktoken>=0.9.0
Provides-Extra: dev
Requires-Dist: pytest-asyncio>=0.20.0; extra == 'dev'
Requires-Dist: pytest-cov>=4.1.0; extra == 'dev'
Requires-Dist: pytest-mock>=3.10.0; extra == 'dev'
Requires-Dist: pytest>=7.0.0; extra == 'dev'
